wield/epics/autocas/__init__.py
wield/epics/autocas/_version.py
wield/epics/autocas/cascore/__init__.py
wield/epics/autocas/cascore/base_backend.py
wield/epics/autocas/cascore/cas9declarative.py
wield/epics/autocas/cascore/cas9program.py
wield/epics/autocas/cascore/cascore.py
wield/epics/autocas/cascore/ctree.py
wield/epics/autocas/cascore/interrupt_delay.py
wield/epics/autocas/cascore/pcaspy_backend.py
wield/epics/autocas/cascore/pyepics_backend.py
wield/epics/autocas/cascore/reactor.py
wield/epics/autocas/cascore/relay_values.py
wield/epics/autocas/cascore/program/__init__.py
wield/epics/autocas/cascore/program/config.py
wield/epics/autocas/cascore/program/list.py
wield/epics/autocas/config/__init__.py
wield/epics/autocas/config/nested_dict_utils.py
wield/epics/autocas/config/toml.py
wield/epics/autocas/config/pytoml/__init__.py
wield/epics/autocas/config/pytoml/core.py
wield/epics/autocas/config/pytoml/parser.py
wield/epics/autocas/config/pytoml/writer.py
wield/epics/autocas/config/pytoml/test/test.py
wield/epics/autocas/config/pytoml/test/test_parser.py
wield/epics/autocas/config/pytoml/test/test_writer.py
wield/epics/autocas/devices/__init__.py
wield/epics/autocas/devices/serial_device.py
wield/epics/autocas/devices/NF3040/__init__.py
wield/epics/autocas/devices/NF3040/ebridge.py
wield/epics/autocas/devices/NF3040/service.py
wield/epics/autocas/devices/NF3040/tempController.py
wield/epics/autocas/devices/NF3040/orig/RS232Test.py
wield/epics/autocas/devices/NF3040/orig/simpleTCRS232.py
wield/epics/autocas/devices/NF3040/orig/tempController.py
wield/epics/autocas/devices/NF3040/test/TST.py
wield/epics/autocas/devices/NF3040/test/__init__.py
wield/epics/autocas/devices/SR560/__init__.py
wield/epics/autocas/devices/SR560/ebridge.py
wield/epics/autocas/devices/SR560/group_controller.py
wield/epics/autocas/devices/SR560/group_ebridge.py
wield/epics/autocas/devices/SR560/service.py
wield/epics/autocas/devices/SR785/__init__.py
wield.epics.autocas-0.4.0.dist-info/Apache-2.0.txt
wield.epics.autocas-0.4.0.dist-info/CC0-1.0.txt
wield.epics.autocas-0.4.0.dist-info/METADATA
wield.epics.autocas-0.4.0.dist-info/NOTICE
wield.epics.autocas-0.4.0.dist-info/WHEEL
wield.epics.autocas-0.4.0.dist-info/top_level.txt
wield.epics.autocas-0.4.0.dist-info/RECORD
